agent_logic/__init__.py
agent_logic/cli.py
agent_logic/core/__init__.py
agent_logic/core/base.py
agent_logic/core/functions.py
agent_logic/core/operations.py
agent_logic/core/predicates.py
agent_logic/core/quantifiers.py
agent_logic/evaluation/__init__.py
agent_logic/evaluation/evaluator.py
agent_logic/evaluation/truth_table.py
agent_logic/models/__init__.py
agent_logic/models/llm_proof_model.py
agent_logic/parsing/__init__.py
agent_logic/parsing/ast_parser.py
agent_logic/parsing/token_parser.py
agent_logic/proofs/__init__.py
agent_logic/proofs/combinatorial_proofs.py
agent_logic/proofs/inference_rules.py
agent_logic/proofs/proof_system.py
agent_logic/proofs/quantifier_rules.py
agent_logic/proofs/sequent_calculus.py
agent_logic/proofs/unification.py
agent_logic/transformations/__init__.py
agent_logic/transformations/equivalences.py
agent_logic/transformations/normal_forms.py
agent_logic/utils/__init__.py
agent_logic/utils/logger.py
agent_logic-0.1.2.dist-info/METADATA
agent_logic-0.1.2.dist-info/WHEEL
agent_logic-0.1.2.dist-info/RECORD
