Metadata-Version: 2.3
Name: agent-logic
Version: 0.1.2
Summary: Modular symbolic logic system supporting proofs, predicates, inference rules, truth tables, and LLM integration with Pydantic models.
License: MIT
Author: William R. Astley
Author-email: wrastley@gmail.com
Requires-Python: >=3.12,<4
Classifier: License :: OSI Approved :: MIT License
Classifier: Programming Language :: Python :: 3
Classifier: Programming Language :: Python :: 3.12
Classifier: Programming Language :: Python :: 3.13
Requires-Dist: pydantic (>=2.10.6,<3.0.0)
